<?xml version="1.0" encoding="utf-8" ?>
<dwsync>
<file name="apple-touch-icon-114x114.png" server="10.0.0.24" local="131051382040000000" remote="131068677600000000" Dst="2" />
<file name="apple-touch-icon-120x120.png" server="10.0.0.24" local="131051382040000000" remote="131068677600000000" Dst="2" />
<file name="apple-touch-icon-144x144.png" server="10.0.0.24" local="131051382040000000" remote="131068677600000000" Dst="2" />
<file name="apple-touch-icon-152x152.png" server="10.0.0.24" local="131051382040000000" remote="131068677600000000" Dst="2" />
<file name="apple-touch-icon-57x57.png" server="10.0.0.24" local="131051382040000000" remote="131068677600000000" Dst="2" />
<file name="apple-touch-icon-60x60.png" server="10.0.0.24" local="131051382040000000" remote="131068677600000000" Dst="2" />
<file name="apple-touch-icon-180x180.png" server="10.0.0.24" local="131051382040000000" remote="131068677600000000" Dst="2" />
<file name="apple-touch-icon-76x76.png" server="10.0.0.24" local="131051382040000000" remote="131068677600000000" Dst="2" />
<file name="favicon-160x160.png" server="10.0.0.24" local="131051382040000000" remote="131068677600000000" Dst="2" />
<file name="apple-touch-icon-72x72.png" server="10.0.0.24" local="131051382040000000" remote="131068677600000000" Dst="2" />
<file name="favicon-16x16.png" server="10.0.0.24" local="131051382040000000" remote="131068677600000000" Dst="2" />
<file name="favicon-192x192.png" server="10.0.0.24" local="131051382040000000" remote="131068677600000000" Dst="2" />
<file name="favicon-32x32.png" server="10.0.0.24" local="131051382040000000" remote="131068677600000000" Dst="2" />
<file name="favicon-96x96.png" server="10.0.0.24" local="131051382040000000" remote="131068677600000000" Dst="2" />
<file name="Highcharts.svg" server="10.0.0.24" local="131051382040000000" remote="131068677600000000" Dst="2" />
<file name="splash.svg" server="10.0.0.24" local="131051382040000000" remote="131068677600000000" Dst="2" />
<file name="sprite.png" server="10.0.0.24" local="131051382040000000" remote="131068677600000000" Dst="2" />
</dwsync>